yarc/__init__.py
yarc/enums.py
yarc/opcode.py
yarc/roomba.py
yarc/sensor.py
yarc-0.9.3.dist-info/LICENSE
yarc-0.9.3.dist-info/METADATA
yarc-0.9.3.dist-info/WHEEL
yarc-0.9.3.dist-info/top_level.txt
yarc-0.9.3.dist-info/RECORD
