Metadata-Version: 2.1
Name: yarc
Version: 0.9.3
Summary: Yet Another Roomba Controller
Home-page: https://github.com/coderforlife/yarc
Author: Jeffrey Bush
Author-email: jeff@coderforlife.com
License: GPLv3
Platform: UNKNOWN
Classifier: Programming Language :: Python :: 3 :: Only
Classifier: Development Status :: 4 - Beta
Classifier: Intended Audience :: Developers
Classifier: Intended Audience :: Education
Classifier: Intended Audience :: Science/Research
Classifier: License :: OSI Approved :: GNU General Public License v3 or later (GPLv3+)
Classifier: Operating System :: OS Independent
Classifier: Topic :: Scientific/Engineering
Classifier: Topic :: System :: Hardware
Requires-Python: >=3.5
Requires-Dist: pyserial
